frvcpy/__init__.py
frvcpy/algorithm.py
frvcpy/core.py
frvcpy/solver.py
frvcpy/translator.py
frvcpy/test/__init__.py
frvcpy/test/test.py
frvcpy/test/data/frvcpy-instance.json
frvcpy/test/data/testdata.json
frvcpy/test/data/vrprep-instance.xml
frvcpy-0.1.1.dist-info/LICENSE
frvcpy-0.1.1.dist-info/METADATA
frvcpy-0.1.1.dist-info/WHEEL
frvcpy-0.1.1.dist-info/entry_points.txt
frvcpy-0.1.1.dist-info/top_level.txt
frvcpy-0.1.1.dist-info/RECORD
