Metadata-Version: 2.1
Name: frvcpy
Version: 0.1.1
Summary: A solver for fixed route vehicle charging problems
Home-page: https://github.com/e-VRO/frvcpy
Author: Nicholas Kullman
Author-email: nicholas.kullman@etu.univ-tours.fr
License: Apache
Platform: UNKNOWN
Classifier: Programming Language :: Python :: 3
Classifier: License :: OSI Approved :: Apache Software License
Classifier: Operating System :: OS Independent
Requires-Python: >=3.6
Requires-Dist: xmltodict
